MANIFEST.in
Makefile
README.rst
__init__.py
debug.py
setup.py
tests.py
virtualenv.py
httphq/__init__.py
httphq/app.py
httphq/compat.py
httphq/manage.py
httphq/settings.py
httphq/taglines.py
httphq/utils.py
httphq.egg-info/PKG-INFO
httphq.egg-info/SOURCES.txt
httphq.egg-info/dependency_links.txt
httphq.egg-info/entry_points.txt
httphq.egg-info/requires.txt
httphq.egg-info/top_level.txt
httphq/templates/human_curl.html
httphq/templates/humans.txt
httphq/templates/index.html
httphq/templates/robots.txt